coderadio/__init__.py
coderadio/__main__.py
coderadio/logger.py
coderadio/messages.py
coderadio/plugins/__init__.py
coderadio/plugins/plug_1_fm_amsterdam_trance_radio.py
coderadio/plugins/plug_bbc_radio_1.py
coderadio/radio.py
coderadio/tui/__init__.py
coderadio/tui/buffers/__init__.py
coderadio/tui/buffers/display.py
coderadio/tui/buffers/listview.py
coderadio/tui/buffers/popup.py
coderadio/tui/buffers/prompt.py
coderadio/tui/commands.py
coderadio/tui/constants.py
coderadio/tui/keybindings.py
coderadio/tui/layout.py
coderadio/tui/styles.py
coderadio/tui/widget/__init__.py
coderadio/tui/widget/display.py
coderadio/tui/widget/listview.py
coderadio/tui/widget/popup.py
coderadio/tui/widget/prompt.py
coderadio/tui/widget/topbar.py
coderadio/utils.py
coderadio-0.0.dev19.dist-info/entry_points.txt
coderadio-0.0.dev19.dist-info/LICENSE
coderadio-0.0.dev19.dist-info/WHEEL
coderadio-0.0.dev19.dist-info/METADATA
coderadio-0.0.dev19.dist-info/RECORD
